signalfive/__init__.py
signalfive-0.0.0.dist-info/METADATA
signalfive-0.0.0.dist-info/WHEEL
signalfive-0.0.0.dist-info/top_level.txt
signalfive-0.0.0.dist-info/RECORD
